<annotation>
	<folder>3rdImages</folder>
	<filename>20200327_224124605_iOS.jpg</filename>
	<path>C:\Users\Nath\Downloads\3rdImages\3rdImages\20200327_224124605_iOS.jpg</path>
	<source>
		<database>Unknown</database>
	</source>
	<size>
		<width>800</width>
		<height>600</height>
		<depth>3</depth>
	</size>
	<segmented>0</segmented>
	<object>
		<name>Traffic_Sign_Stop</name>
		<pose>Unspecified</pose>
		<truncated>0</truncated>
		<difficult>0</difficult>
		<bndbox>
			<xmin>156</xmin>
			<ymin>188</ymin>
			<xmax>196</xmax>
			<ymax>225</ymax>
		</bndbox>
	</object>
	<object>
		<name>Traffic_Sign_30</name>
		<pose>Unspecified</pose>
		<truncated>0</truncated>
		<difficult>0</difficult>
		<bndbox>
			<xmin>256</xmin>
			<ymin>172</ymin>
			<xmax>358</xmax>
			<ymax>282</ymax>
		</bndbox>
	</object>
	<object>
		<name>Traffic_Sign_No_Entry</name>
		<pose>Unspecified</pose>
		<truncated>0</truncated>
		<difficult>0</difficult>
		<bndbox>
			<xmin>589</xmin>
			<ymin>174</ymin>
			<xmax>632</xmax>
			<ymax>220</ymax>
		</bndbox>
	</object>
</annotation>
