<annotation>
	<folder>OneDrive_1_09-03-2020</folder>
	<filename>20200309_145202489_iOS.jpg</filename>
	<path>C:\Users\Nath\Downloads\OneDrive_1_09-03-2020\20200309_145202489_iOS.jpg</path>
	<source>
		<database>Unknown</database>
	</source>
	<size>
		<width>800</width>
		<height>600</height>
		<depth>3</depth>
	</size>
	<segmented>0</segmented>
	<object>
		<name>person</name>
		<pose>Unspecified</pose>
		<truncated>0</truncated>
		<difficult>0</difficult>
		<bndbox>
			<xmin>356</xmin>
			<ymin>352</ymin>
			<xmax>454</xmax>
			<ymax>479</ymax>
		</bndbox>
	</object>
	<object>
		<name>Traffic_Sign_No_Entry</name>
		<pose>Unspecified</pose>
		<truncated>1</truncated>
		<difficult>0</difficult>
		<bndbox>
			<xmin>1</xmin>
			<ymin>230</ymin>
			<xmax>99</xmax>
			<ymax>321</ymax>
		</bndbox>
	</object>
	<object>
		<name>Traffic_Sign_50</name>
		<pose>Unspecified</pose>
		<truncated>0</truncated>
		<difficult>0</difficult>
		<bndbox>
			<xmin>340</xmin>
			<ymin>179</ymin>
			<xmax>411</xmax>
			<ymax>250</ymax>
		</bndbox>
	</object>
	<object>
		<name>Traffic_Sign_30</name>
		<pose>Unspecified</pose>
		<truncated>0</truncated>
		<difficult>0</difficult>
		<bndbox>
			<xmin>505</xmin>
			<ymin>142</ymin>
			<xmax>561</xmax>
			<ymax>197</ymax>
		</bndbox>
	</object>
	<object>
		<name>Traffic_Sign_Stop</name>
		<pose>Unspecified</pose>
		<truncated>0</truncated>
		<difficult>0</difficult>
		<bndbox>
			<xmin>701</xmin>
			<ymin>177</ymin>
			<xmax>771</xmax>
			<ymax>253</ymax>
		</bndbox>
	</object>
</annotation>
